PyDeepLib/__init__.py
PyDeepLib/layers.py
PyDeepLib/loggingin.py
PyDeepLib/speedfilein.py
PyDeepLib/tensorclass.py
PyDeepLib-0.0.1.dist-info/METADATA
PyDeepLib-0.0.1.dist-info/WHEEL
PyDeepLib-0.0.1.dist-info/top_level.txt
PyDeepLib-0.0.1.dist-info/RECORD
