Metadata-Version: 2.1
Name: PyDeepLib
Version: 0.0.1
Summary: A simple library for deep learning
Home-page: https://github.com/y-a-r-i-k/PDLib
Author: yarik_g
Author-email: gusevyaroslaveggg666@gmail.com
Project-URL: Documentation, https://github.com/y-a-r-i-k/PDLib
Keywords: example python
Classifier: Programming Language :: Python :: 3.10
Classifier: License :: OSI Approved :: MIT License
Classifier: Operating System :: OS Independent
Requires-Python: >=3.9
Requires-Dist: requests (>=2.25.1)
Requires-Dist: numpy
